devtools_ip_generator/__init__.py
devtools_ip_generator-1.0.1.dist-info/METADATA
devtools_ip_generator-1.0.1.dist-info/WHEEL
devtools_ip_generator-1.0.1.dist-info/top_level.txt
devtools_ip_generator-1.0.1.dist-info/RECORD
